{"stats":{"minecraft:picked_up":{"nondystmod:example_block":2,"minecraft:sand":10,"minecraft:dirt":8},"minecraft:used":{"minecraft:redstone_torch":1,"minecraft:sand":16,"nondystmod:example_item":5,"minecraft:tnt":1,"nondystmod:example_block":58},"minecraft:custom":{"minecraft:time_since_rest":21830,"minecraft:crouch_one_cm":40,"minecraft:sprint_one_cm":1276,"minecraft:play_time":21830,"minecraft:walk_one_cm":14844,"minecraft:sneak_time":221,"minecraft:walk_under_water_one_cm":4055,"minecraft:mob_kills":4,"minecraft:drop":2,"minecraft:jump":32,"minecraft:leave_game":25,"minecraft:walk_on_water_one_cm":452,"minecraft:time_since_death":21830,"minecraft:total_world_time":53519,"minecraft:fly_one_cm":68274},"minecraft:dropped":{"nondystmod:example_block":2},"minecraft:killed":{"minecraft:cod":3,"minecraft:pig":1}},"DataVersion":3465}